vibe_agent/__init__.py
vibe_agent/dialogue_layer.py
vibe_agent/infer_layer.py
vibe_agent-0.0.3.dist-info/licenses/LICENSE
vibe_agent-0.0.3.dist-info/METADATA
vibe_agent-0.0.3.dist-info/WHEEL
vibe_agent-0.0.3.dist-info/top_level.txt
vibe_agent-0.0.3.dist-info/RECORD
