Metadata-Version: 2.4
Name: vibe-agent
Version: 0.0.3
Summary: A Vibe Coding flavored AI Agent SDK based on OpenAI.
Author: ShiXuhao
License-Expression: MIT
Project-URL: Homepage, https://github.com/ShiXuhao/vibe-agent
Project-URL: Bug Tracker, https://github.com/ShiXuhao/vibe-agent/issues
Requires-Python: >=3.8
License-File: LICENSE
Requires-Dist: openai>=1.0.0
Requires-Dist: pydantic>=2.0.0
Dynamic: license-file
